[
  {
    "id": "aldek",
    "name": "Aldek"
  },
  {
    "id": "aria",
    "name": "Aria"
  },
  {
    "id": "burnett",
    "name": "Burnett"
  },
  {
    "id": "charlotte",
    "name": "Charlotte"
  },
  {
    "id": "ella",
    "name": "Ella"
  },
  {
    "id": "elyza",
    "name": "Elyza"
  },
  {
    "id": "emille",
    "name": "Emille"
  },
  {
    "id": "garret",
    "name": "Garret"
  },
  {
    "id": "gryza",
    "name": "Gryza"
  },
  {
    "id": "lestat",
    "name": "Lestat"
  },
  {
    "id": "lydia",
    "name": "Lydia"
  },
  {
    "id": "noor",
    "name": "Noor"
  },
  {
    "id": "noron",
    "name": "Noron"
  },
  {
    "id": "oola",
    "name": "Oola"
  },
  {
    "id": "owen",
    "name": "Owen"
  },
  {
    "id": "ryslette",
    "name": "Ryslette"
  },
  {
    "id": "sally",
    "name": "Sally"
  },
  {
    "id": "tovu",
    "name": "Tovu"
  },
  {
    "id": "wrydio",
    "name": "Wrydio"
  },
  {
    "id": "xarya",
    "name": "Xarya"
  }
]
